mrtsboosting/__init__.py
mrtsboosting/mrtsboosting.py
mrtsboosting-0.1.0.dist-info/licenses/LICENSE
mrtsboosting-0.1.0.dist-info/METADATA
mrtsboosting-0.1.0.dist-info/WHEEL
mrtsboosting-0.1.0.dist-info/top_level.txt
mrtsboosting-0.1.0.dist-info/RECORD
