Metadata-Version: 2.4
Name: mrtsboosting
Version: 0.1.0
Summary: MRTSBoosting: Multivariate Robust Time Series Boosting
Home-page: https://github.com/byususen/mrtsboosting
Author: Bayu Suseno
Author-email: bayu.suseno@outlook.com
License: MIT
Classifier: Programming Language :: Python :: 3
Classifier: License :: OSI Approved :: MIT License
Classifier: Operating System :: OS Independent
Requires-Python: >=3.8
License-File: LICENSE
Requires-Dist: numpy
Requires-Dist: pandas
Requires-Dist: scikit-learn
Requires-Dist: xgboost
Requires-Dist: numba
Requires-Dist: joblib
Requires-Dist: astropy
Dynamic: author
Dynamic: author-email
Dynamic: classifier
Dynamic: description
Dynamic: description-content-type
Dynamic: home-page
Dynamic: license
Dynamic: license-file
Dynamic: requires-dist
Dynamic: requires-python
Dynamic: summary
